yasmll/__init__.py
yasmll/_version.py
yasmll/layers.py
yasmll/models.py
yasmll/yasmll.py
yasmll/tests/__init__.py
yasmll/tests/conftest.py
yasmll/tests/test_examples.py
yasmll-0.1.0.dist-info/AUTHORS.rst
yasmll-0.1.0.dist-info/LICENSE
yasmll-0.1.0.dist-info/METADATA
yasmll-0.1.0.dist-info/WHEEL
yasmll-0.1.0.dist-info/top_level.txt
yasmll-0.1.0.dist-info/RECORD
